{
  "timestamp": "2025-12-12T02:53:44.954359",
  "paper_id": "2512.09600v1",
  "analysis": "### 1. 研究主题分析\n本文的核心研究内容是建立并验证一个**先进的微波SQUID（超导量子干涉器件）多路复用器模型**，该模型能够精确描述其共振特性对读出功率的依赖关系。研究聚焦于**射频SQUID（rf-SQUID）** 在微波频率下的行为建模，特别关注两个关键因素：**读出功率效应**和**约瑟夫森结的非均匀性**。这属于加速器物理中**粒子探测器读出电子学**的分支，具体涉及**超导探测器信号读出与处理技术**，常用于高能物理实验（如暗物质探测、X射线光谱学）中的低噪声信号放大与多通道复用。技术路线基于**电路量子电动力学（cQED）理论**，通过改进的电磁模型结合非线性约瑟夫森效应，对SQUID与谐振器的耦合系统进行数值模拟，并与实验数据对比验证。\n\n### 2. 技术创新点\n论文的主要创新在于提出了一个**涵盖更广参数范围且物理细节更丰富的综合模型**。具体包括：  \n- **扩展了模型的适用性**：将SQUID屏蔽参数范围扩展至β_L < 1，覆盖了所有实际设计参数，突破了传统模型仅适用于β_L << 1的限制。  \n- **首次引入约瑟夫森结非均匀性的影响**：通过支持非正弦电流-相位关系（CPR），能够模拟隧道结势垒不均匀导致的器件行为偏差，这是以往模型忽略的关键物理因素。  \n- **改进读出功率依赖性描述**：模型在宽功率范围内（包括超出典型工作条件的高功率）仍与实验数据高度吻合，优于现有线性化或近似模型。技术难点在于**统一处理非线性、非理想约瑟夫森动力学与微波谐振的耦合**，以及从微观结不均匀性到宏观电路响应的跨尺度建模。\n\n### 3. 应用价值评估\n该研究在加速器物理领域具有重要的应用价值，主要服务于**基于超导探测器的前沿实验**。例如：  \n- **应用于同步辐射光源**：如X射线自由电子激光（XFEL）的高分辨率光谱仪，需多像素超导探测器实现高通量、低噪声测量。  \n- **应用于高能物理实验**：如暗物质直接探测（超导量子位探测器）、中微子实验等，需大规模探测器阵列的低功耗多路读出。  \n- **性能提升方面**：模型支持更精确的器件优化，可提高多路复用器的**动态范围、线性度和通道密度**，降低串扰，从而提升整个探测系统的灵敏度和数据获取效率。\n\n### 4. 技术难点解析\n论文解决的关键技术难题包括：  \n- **传统模型的局限性**：现有模型在β_L接近1或高读出功率时失效，因未充分考虑SQUID的非线性响应及结非理想性。  \n- **约瑟夫森结非均匀性的量化影响**：不均匀势垒导致CPR偏离正弦形式，进而影响谐振频率偏移和功率响应，此前缺乏有效建模手段。  \n- **解决方案**：通过**引入广义CPR函数**（如包含高阶谐波项）并结合全电路仿真，直接集成非均匀性参数；同时采用**自洽数值方法**求解耦合系统方程，避免过度简化。尚未完全解决的挑战包括：**极端低温下的动态效应建模**、**大规模阵列中的交叉耦合精确预测**，以及**制造工艺波动对结不均匀性的统计描述**。\n\n### 5. 研究意义评价\n- **理论意义**：推动了超导电子学器件物理建模的精细化，将微观结特性与宏观电路性能直接关联，为非线性量子电路理论提供了新案例。  \n- **工程实践意义**：为SQUID多路复用器的设计与优化提供了可靠工具，有助于缩短研发周期、降低实验试错成本，并支持定制化器件开发。  \n- **国际前沿地位**：该研究处于**超导读出技术的前沿**，针对下一代大型实验（如国际线性对撞机ILC的探测器升级）的需求，与国际上如美国费米实验室、欧洲核子研究中心（CERN）的相关研究形成互补。\n\n### 6. 未来发展展望\n后续研究方向可能包括：  \n- **扩展至其他超导器件**：如应用于微波动能电感探测器（MKID）或量子比特读出电路的多路复用模型。  \n- **集成人工智能优化**：利用机器学习加速模型参数扫描与器件逆向设计。  \n- **面向更大规模阵列**：研究高密度集成下的热管理、串扰抑制及校准算法。  \n应用前景广阔，预计将推动**量子传感与高能物理探测器的模块化、高性能读出系统**发展。需进一步研究的问题包括：**非均匀性的原位表征方法**、**极端环境（强磁场、高辐照）下的模型适应性**，以及**低成本可扩展制造工艺的模型对接**。",
  "classification": {
    "category": "分类编号: 6\n分类名称: 超导技术\n置信度: high",
    "confidence": 0.8
  },
  "keywords": [
    "microwave SQUID multiplexer",
    "rf-SQUID",
    "Josephson junction",
    "current-phase relation",
    "screening parameter",
    "tunnel barrier inhomogeneities",
    "resonance characteristics",
    "readout power dependence"
  ],
  "summary": "本文提出并验证了一个先进的微波SQUID多路复用器模型，其核心贡献在于首次将约瑟夫森结的非均匀性和宽范围读出功率效应纳入模型，显著提升了器件非线性响应的预测精度。这一模型为优化用于高能物理与同步辐射探测的超导读出系统性能提供了关键的设计工具。",
  "error": null
}