{
  "timestamp": "2025-08-30T02:38:17.377958",
  "paper_id": "2508.19662v1",
  "analysis": "### 1. 研究主题分析\n本论文的核心研究内容是探索蓝色核心螺旋波放电（blue-core helicon discharge）的过渡特性。螺旋波放电是等离子体物理中的重要现象，特别是在高密度等离子体产生方面具有关键作用。蓝色核心状态是螺旋波放电中的一种特殊模式，其特征是等离子体中心区域呈现蓝色发光，通常与高电子密度和特定的波-粒子相互作用相关。该研究属于加速器物理中的等离子体源技术分支，特别是与离子源和等离子体加速器相关的领域。研究采用的技术路线结合了实验诊断和数值模拟：通过朗缪尔探针、光学发射光谱仪和高速相机等多种诊断手段在MPS-LD装置上测量等离子体参数，同时利用基于麦克斯韦方程和冷等离子体介电张量的电磁求解器（EMS）进行波场和功率吸收的数值计算，从而全面分析过渡阶段的物理特性。\n\n### 2. 技术创新点\n论文的主要技术创新点在于首次系统性地研究了蓝色核心螺旋波放电的过渡特性，尤其是电子密度和电子温度在过渡过程中的反向跳变行为。此外，研究通过多诊断手段的结合和数值模拟的补充，提供了实验上难以直接获取的波场结构细节。相比现有技术，该研究突破了以往对蓝色核心现象仅关注稳态特性的局限，深入探讨了其动态过渡过程。技术难点包括高时空分辨率的等离子体参数测量（例如电子密度的径向分布和高速振荡捕捉），以及波-等离子体相互作用的数值建模。这些难点通过多诊断协同和电磁求解器的应用得到了部分解决，但过渡过程中的非线性效应和模式转换的精确捕捉仍是挑战。\n\n### 3. 应用价值评估\n这项研究在加速器物理领域具有重要的应用价值，特别是在等离子体离子源和聚变装置中的等离子体加热与维持方面。蓝色核心螺旋波放电可用于高效产生高密度等离子体，适用于离子加速器、材料处理装置和磁约束聚变设备（如托卡马克的辅助加热系统）。通过优化蓝色核心过渡的控制，可以提升等离子体源的稳定性和效率，从而改善加速器的束流品质和能量利用效率。例如，在离子注入或等离子体推进器中，高密度且稳定的等离子体生成是关键需求，此项研究为相关技术提供了理论依据和实验参考。\n\n### 4. 技术难点解析\n论文解决的关键技术难题包括蓝色核心过渡过程中电子密度和温度的反向变化机制、波场结构的演化以及等离子体不稳定的表征。例如，电子密度径向分布的局域化和电子温度的“W”形分布是过渡阶段的典型特征，但其物理成因复杂，涉及波-粒子共振和能量吸收的时空非均匀性。研究通过多诊断手段（如朗缪尔探针和高速相机）捕捉了等离子体柱的径向振荡和方位不稳定性，同时利用电磁求解器模拟了波场在过渡期间的变化，揭示了功率吸收的分布特性。然而，尚未完全解决的技术挑战包括过渡触发机制的精确预测、非线性效应的全面建模，以及如何在实际装置中主动控制蓝色核心模式的稳定性。\n\n### 5. 研究意义评价\n该研究对加速器物理学科的发展具有重要理论意义，它深化了对螺旋波放电中模式转换物理的理解，特别是波-等离子体相互作用和非平衡态动力学过程。蓝色核心过渡的研究为高密度等离子体的生成和维持提供了新视角，对等离子体物理的理论模型（如介电张量和波传播方程）有补充作用。在工程实践上，这项研究为设计高效等离子体源和优化加热方案提供了指导，例如通过调节磁场强度和背景气压来控制电子密度和温度分布。在国际研究前沿中，蓝色核心螺旋波放电是等离子体源领域的热点课题，本研究的综合实验与模拟方法处于先进水平，为后续研究提供了重要参考。\n\n### 6. 未来发展展望\n可能的后续研究方向包括进一步探索蓝色核心过渡的触发机制，例如通过更精细的时空诊断（如微波干涉仪或激光散射）捕捉波-粒子相互作用的细节，以及开发结合热等离子体效应的扩展数值模型。此外，研究可转向主动控制蓝色核心模式的应用，例如通过反馈调节天线功率或磁场配置来抑制不稳定性。预期的应用前景包括在聚变装置（如ITER的离子回旋加热系统）和工业等离子体设备中实现更稳定高效的高密度等离子体操作。需要进一步研究的问题包括过渡过程中的非线性动力学、多模式耦合效应，以及蓝色核心状态在复杂磁场几何（如仿星器或线性装置中的非均匀场）中的行为差异。",
  "classification": {
    "category": "分类编号: 9\n分类名称: 其他\n置信度: high",
    "confidence": 0.8
  },
  "keywords": [
    "helicon discharge",
    "electron density",
    "electron temperature",
    "Langmuir probe",
    "optical emission spectrometer",
    "wave magnetic field",
    "wave electric field",
    "power absorption"
  ],
  "summary": "该论文首次系统揭示了蓝色核心螺旋波放电的过渡特性，发现了电子密度与温度的反向跳变现象，通过实验与数值模拟相结合的方法深化了对波-等离子体相互作用机制的理解，为高密度等离子体源在加速器和聚变装置中的优化应用提供了重要理论依据。",
  "error": null
}