{
  "timestamp": "2025-11-21T02:42:47.428839",
  "paper_id": "2511.13862v1",
  "analysis": "### 1. 研究主题分析\n本论文的核心研究内容是分析X9级太阳耀斑中快速耀斑带下流现象的物理机制。通过IRIS卫星在Si IV 1402.77 nm谱线的观测数据，作者检测到持续15分钟、速度达150-217 km/s的快速下流现象，并发现这些下流可分为两个不同阶段。研究属于太阳物理和空间等离子体物理范畴，与加速器物理中的带电粒子加速和能量转换过程密切相关。技术路线采用多仪器联合观测（IRIS、ASO-S/HXI、LYRA）结合机器学习方法，通过光谱分析、硬X射线能谱诊断和多变量聚类算法，系统揭示了下流现象的双重物理起源。\n\n### 2. 技术创新点\n本研究的核心创新在于首次明确区分了太阳耀斑中快速下流现象的两种不同物理机制：早期阶段与耀斑能量释放相关的色球凝聚，以及后期阶段与耀斑诱导的日冕雨相关的 footpoint 下流。方法学上创新性地将硬X射线能谱分析（显示非热辐射特征）与机器学习K-means聚类结合，定量解析谱线轮廓演化。相比传统单一机制解释，该研究通过多波段同步观测数据揭示了更复杂的动力学过程。主要技术难点在于区分不同阶段下流信号的时空关联性，以及从复杂观测数据中提取准周期振荡信号。\n\n### 3. 应用价值评估\n该研究对加速器物理领域的价值主要体现在等离子体约束和能量耗散机制的理解上。耀斑中的磁重联过程与环形加速器中的束流不稳定性具有相似物理本质，其下流现象的研究可为环形粒子加速器中的束流损失机制提供参考。特别对同步辐射光源和未来环形对撞机而言，该研究揭示的磁流体振荡与粒子加速的耦合机制，有助于优化磁约束系统和能量提取效率。实际应用中可能影响ITER等聚变装置等离子体控制策略的改进。\n\n### 4. 技术难点解析\n论文成功解决了两个关键技术难题：一是区分不同物理起源的下流信号，通过多仪器时序关联分析实现了机制分离；二是从复杂观测数据中提取准周期振荡特征，采用谱分析方法识别出稳定的50秒周期振荡。创新解决方案包括：利用硬X射线非热辐射作为能量释放示踪剂，结合Lyman-alpha辐射变化建立因果链；开发机器学习聚类算法自动分类谱线轮廓演化。尚未完全解决的挑战包括：磁流体振荡的激发机制仍需量化，下流物质与磁场结构的三维耦合关系需要更高分辨率观测验证。\n\n### 5. 研究意义评价\n在理论层面，该研究首次建立了耀斑下流现象的双阶段物理模型，完善了磁重联能量释放的色球响应理论。对太阳耀斑模型中的“标准模型”和“日冕雨”模型提供了直接观测证据。在工程实践方面，其揭示的磁流体振荡规律对空间天气预报和卫星防护具有指导意义。该研究位于太阳物理国际前沿，通过最新空间观测设备（ASO-S）获得的高质量数据，为理解恒星活动中的粒子加速过程设立了新的研究范式。\n\n### 6. 未来发展展望\n后续研究可重点关注：1）开发三维磁流体动力学数值模型，定量重现双阶段下流现象；2）扩展研究其他耀斑等级的下流特征，建立速度-能量释放的标度律；3）结合欧洲太阳望远镜（EST）等下一代地面设备，获取更高时空分辨率观测。预期应用前景包括改进空间天气预警模型，以及为聚变装置等离子体控制提供新思路。亟待解决的关键问题包括：准周期振荡的能量来源、不同下流机制的质量输运效率比较、以及磁重联率与下流速度的定量关系等。",
  "classification": {
    "category": "分类编号: 9\n分类名称: 其他\n置信度: high",
    "confidence": 0.8
  },
  "keywords": [
    "chromospheric condensations",
    "non-thermal emission",
    "MHD oscillations",
    "hard X-ray spectral analysis",
    "quasi-periodic pulsations",
    "K-means clustering",
    "Doppler velocities",
    "magnetic arcade"
  ],
  "summary": "该研究首次明确区分了太阳耀斑中快速下流现象的双重物理起源：早期阶段与耀斑能量释放相关的色球凝聚，以及后期阶段与耀斑诱导的日冕雨相关的足点下流。这一发现不仅完善了磁重联能量释放的色球响应理论，还为粒子加速器中的束流损失机制和聚变装置的等离子体控制提供了重要参考。",
  "error": null
}