{
  "timestamp": "2025-10-12T02:41:32.481434",
  "paper_id": "2501.01869v2",
  "analysis": "### 1. 研究主题分析\n本论文的核心研究内容是针对量子蒙特卡罗（QMC）数据在虚时间域到实频率域解析延拓问题中的最大熵方法（MEM）优化。解析延拓是量子多体问题中的关键数学工具，用于从虚时间关联函数中提取动态谱函数，但该过程具有严重的病态性。论文聚焦于改进MEM中的优化算法，通过引入对偶牛顿法替代传统的Bryan算法，以提升在噪声存在下的计算精度和稳定性。从领域归属看，这项工作属于计算物理与量子多体理论的交叉领域，虽未直接涉及加速器硬件，但其方法论对加速器物理中束流动力学模拟、等离子体不稳定性分析等需要处理量子统计数据的场景具有重要支撑作用。\n\n技术路线上，作者建立了MEM的凸优化对偶形式，通过理论证明对偶问题的光滑性优于原问题，并设计了基于牛顿法的二阶优化算法。该方法结合了正则化理论与误差分析，在保持MEM概率框架的同时规避了Bryan算法中存在的协方差矩阵奇异性问题。\n\n### 2. 技术创新点\n论文的核心创新在于提出了基于对偶形式的牛顿优化算法，并给出了严格的误差界证明。相较于传统Bryan算法仅使用特征子空间近似求解，新算法通过凸优化理论将原问题转化为对偶问题，保证了解的全局收敛性。具体突破体现在三方面：一是证明了目标函数的强凸性，使牛顿法具有二次收敛速率；二是给出了算法迭代误差的解析上界，为结果可靠性提供量化依据；三是通过数值实验证实新算法在噪声数据下仍能保持稳定的谱函数重建。\n\n技术难点主要在于如何将MEM中的非光滑正则项转化为可微对偶形式，以及设计高效的Hessian矩阵计算方法。作者通过Legendre变换将熵正则项对偶化，并利用自动微分技术实现二阶导数计算，这些措施有效克服了传统方法在病态协方差矩阵下的数值不稳定性。\n\n### 3. 应用价值评估\n在加速器物理领域，该研究对束流-等离子体相互作用、尾场效应分析等需要处理量子涨落的过程具有重要价值。例如在自由电子激光装置中，电子束与wiggler磁场的相互作用建模需要精确的电子动态响应函数，而传统MEM方法在实验噪声下可能产生虚假谱峰。新算法通过改进的误差控制机制，能够更可靠地重建集体激发模式（如论文中验证的电子气旋子特征），这对理解束流不稳定性机理至关重要。\n\n在等离子体加速器、电子回旋共振加热等场景中，该方法可用于从QMC模拟数据中提取更准确的介电函数，进而优化能量沉积预测。相比传统方法，改进的MEM有望提升对复杂系统中多尺度物理过程的建模精度，为加速器设计提供更可靠的理论依据。\n\n### 4. 技术难点解析\n论文成功解决了MEM实施中的两个关键难题：一是Bryan算法因截断小特征值导致的系统误差积累问题，二是噪声数据下谱函数振荡抑制与特征保持的平衡问题。创新解决方案是通过对偶重构将原问题的维度从谱函数空间转换到拉格朗日乘子空间，利用对偶变量的物理约束（如非负性）自然保证了解的物理合理性。\n\n尚未完全解决的挑战包括：对于强关联体系出现的多峰谱函数，该方法仍依赖初始模型的选择；在极高噪声水平（如信噪比低于10dB）下的自适应正则化参数选取机制仍需完善；对非平衡态过程的扩展尚未验证，这些都将影响其在加速器瞬态过程分析中的直接应用。\n\n### 5. 研究意义评价\n在理论层面，这项工作通过建立MEM的严格优化框架，推动了计算物理中逆问题研究方法学的发展。提出的误差界证明方法为其他谱重建算法提供了可借鉴的分析范式，特别是对加速器物理中常用的束流诊断数据处理（如从相干辐射谱反推束团分布）具有参考价值。\n\n在工程实践方面，该算法已成功应用于温密物质条件下均匀电子气的旋子特征研究，证实其处理真实实验数据的能力。相较于国际同类研究（如Sandia国家实验室的随机解析延拓方法），该工作首次在MEM框架内实现可证明的误差控制，处于计算谱方法研究前沿。\n\n### 6. 未来发展展望\n后续研究可沿三个方向展开：一是将算法扩展至相对论性量子体系，以适应高能加速器中的极端相对论束流模拟；二是开发基于机器学习的先验模型选择方法，降低对人工经验的依赖；三是与实时QMC采样结合，构建端到端的动态谱计算流程。\n\n在应用前景方面，该技术有望集成到主流加速器设计软件（如MAD-X、ASTRA）的束流-物质相互作用模块中，特别对未来高亮度对撞机中的束流热化分析、等离子体尾场加速器的非线性效应建模具有潜在价值。需要进一步研究的问题包括算法在GPU集群上的并行化实现，以及针对特定加速器场景的定制化正则化方案设计。",
  "classification": {
    "category": "分类编号: 9\n分类名称: 其他\n置信度: high",
    "confidence": 0.8
  },
  "keywords": [
    "maximum entropy method",
    "analytic continuation",
    "quantum Monte Carlo",
    "dual Newton optimization",
    "lattice quantum chromodynamics",
    "warm dense matter",
    "dispersion relation",
    "roton-type feature"
  ],
  "summary": "该论文提出了一种基于对偶牛顿法的最大熵方法改进算法，通过将解析延拓问题转化为凸优化对偶形式，显著提升了量子蒙特卡罗数据在噪声环境下谱函数重建的精度和稳定性。这一创新不仅解决了传统Bryan算法的数值不稳定性问题，还为加速器物理中束流动力学模拟等需要处理量子涨落的场景提供了更可靠的计算工具。",
  "error": null
}