{
  "timestamp": "2025-09-12T02:31:54.001547",
  "paper_id": "2502.21198v3",
  "analysis": "### 1. 研究主题分析\n该论文的核心研究内容是开发基于深度学习的自主触发系统，用于广延大气簇射（EAS）的无线电探测。研究聚焦于解决在强射频干扰环境下传统触发系统的局限性，特别是针对大倾角宇宙线事件的探测难题。这属于宇宙线物理与粒子天体物理交叉领域，具体涉及加速器物理中的探测器触发技术分支。技术路线采用全卷积神经网络处理MHz级采样率的无线电信号，结合HLS4ML工具进行FPGA硬件实现，实现了从算法设计到硬件部署的完整验证流程。\n\n### 2. 技术创新点\n论文提出了基于深度学习的无线电信号实时触发新方法，创新点包括：首次将全卷积网络应用于EAS无线电信号的毫秒级实时处理；开发了基于HLS4ML的FPGA量化部署方案；实现了在保持高精度（AUC>0.99）的同时达到微秒级延迟的性能突破。相比传统阈值触发方法，新方法在相同误报率下探测效率提升显著，特别是在强干扰环境中对大倾角事件的探测能力有质的飞跃。技术难点在于如何在严格延迟约束下保持神经网络精度，以及解决射频信号的非平稳特性带来的训练挑战。\n\n### 3. 应用价值评估\n该研究在宇宙线观测领域具有重要应用价值，特别适用于下一代大型宇宙线观测站如GRAND、BEACON等项目的触发系统。其低延迟、高精度的特性可使观测站实现纯无线电触发，摆脱对传统粒子探测器的依赖。这将显著提升观测站对超高能宇宙线和大倾角事件的探测能力，扩展有效观测视场，同时为探测超高能中微子提供新的技术路径。在加速器物理领域，类似技术也可应用于束流诊断和在线监测系统。\n\n### 4. 技术难点解析\n论文成功解决了三个关键技术难题：首先是强射频干扰环境下的信号识别问题，通过使用真实噪声与模拟信号结合的训练方案提升了模型鲁棒性；其次是严格延迟约束下的神经网络优化，采用全卷积架构和模型量化技术实现了微秒级推理；第三是硬件资源约束下的精度保持，通过HLS4ML工具链实现了FPGA部署时0.997到0.996的极小精度损失。尚未完全解决的挑战包括极端干扰环境下的泛化能力，以及多站点联合触发的时间同步问题。\n\n### 5. 研究意义评价\n该研究在理论层面证明了深度学习在粒子探测器触发系统中的可行性，为高能物理实验的实时数据处理提供了新范式。在工程实践层面，给出了完整的FPGA实现方案，具有直接指导价值。该工作处于国际研究前沿，与欧洲核子研究中心等机构开展的FPGA机器学习研究相呼应，但创新性地专注于宇宙线探测这一特定应用场景，其技术路线对其他粒子探测器系统具有重要参考意义。\n\n### 6. 未来发展展望\n后续研究可朝多个方向拓展：一是开发更轻量化的网络架构以适应更大规模的阵列部署；二是研究自适应学习机制以应对动态变化的干扰环境；三是探索多模态数据融合触发，结合粒子探测器与无线电信号。预期应用前景包括平方公里阵列（SKA）等大型射电天文项目的实时信号处理，以及加速器束流损失监测系统。需要进一步研究的问题包括模型在极端天气条件下的稳定性，以及长期运行中的可靠性验证。",
  "classification": {
    "category": "分类编号: 9\n分类名称: 其他\n置信度: high",
    "confidence": 0.8
  },
  "keywords": [
    "Extensive air showers",
    "Radio detection",
    "FPGA triggering",
    "Deep learning",
    "Cosmic-ray observatories",
    "Radio-frequency interference",
    "High-inclined events",
    "Ultra-high-energy neutrinos"
  ],
  "summary": "该论文开发了基于深度学习的FPGA实时触发系统，首次实现广延大气簇射无线电信号的毫秒级高精度识别，解决了强干扰环境下传统触发方法的局限性，为下一代宇宙线观测站提供了创新性技术方案。",
  "error": null
}