{
  "timestamp": "2025-08-05T03:22:41.208089",
  "paper_id": "2508.00455v1",
  "analysis": "### 1. 研究主题分析  \n论文的核心研究内容是开发一种可调谐、相位锁定的硬X射线脉冲序列生成技术，利用自种子X射线自由电子激光（FEL）实现高精度振幅和相位控制。研究属于加速器物理中的**自由电子激光技术**分支，具体聚焦于**相干辐射调控**和**超快脉冲整形**。技术路线基于“fresh-bunch”自种子方案，结合电子束整形（通过开槽箔片和尾波场结构）和相位锁定方法，实现了飞秒级时间调制的相干辐射。该方法突破了传统FEL在相位控制上的限制，为量子光学实验提供了新工具。\n\n---\n\n### 2. 技术创新点  \n论文的创新点包括：  \n1. **相位锁定技术**：首次在硬X射线波段（9.7 keV）实现相位锁定的脉冲序列，相位抖动低至0.1阿秒，远超现有FEL的稳定性。  \n2. **电子束整形**：采用开槽箔片和尾波场结构对电子束进行精确调制，解决了传统FEL中电子束能量分布不均匀的问题。  \n3. **可调谐性**：脉冲延迟可在4.5–11.9 fs范围内自由调节，且相对相位可编程控制。  \n技术难点在于电子束与辐射场的精确同步，以及抑制噪声引起的相位漂移。作者通过优化束流动力学和反馈系统解决了这一问题。\n\n---\n\n### 3. 应用价值评估  \n该技术在**相干光谱学**和**量子光学实验**中具有重要价值，例如X射线瞬态吸收谱和双色泵浦-探测实验。适用的加速器设施包括欧洲XFEL、LCLS-II等硬X射线FEL装置。其核心价值在于提升了FEL的**时间分辨能力**和**相位相干性**，为研究超快电子动力学和量子态操控提供了新手段。此外，该技术可能推动硬X射线任意波形发生器的发展，扩展FEL在材料科学和化学中的应用场景。\n\n---\n\n### 4. 技术难点解析  \n关键技术难题包括：  \n1. **电子束与辐射场的相位匹配**：通过尾波场结构精确调控电子束微结构，确保与种子激光的相位同步。  \n2. **相位抖动抑制**：采用闭环反馈系统降低噪声影响，将抖动控制在阿秒量级。  \n3. **脉冲能量稳定性**：优化自种子过程以提高输出脉冲能量的均匀性。  \n未完全解决的挑战包括更高光子能量（>20 keV）的扩展性，以及多脉冲序列的复杂相位控制。\n\n---\n\n### 5. 研究意义评价  \n理论意义在于首次将微波和光学波段的量子态操控技术推广到硬X射线领域，填补了FEL相位控制的空白。工程实践上，该技术为FEL用户实验提供了新工具，例如阿秒级时间分辨实验。在国际前沿中，该研究处于**领先地位**，与欧洲XFEL的脉冲整形研究形成互补，但更强调相位锁定精度。其成果可能成为未来FEL升级的参考标准。\n\n---\n\n### 6. 未来发展展望  \n后续研究方向包括：  \n1. **扩展光子能量范围**：验证技术在更高能量（如20 keV以上）的适用性。  \n2. **多脉冲序列优化**：开发更多脉冲数（如五脉冲或连续波形）的生成方法。  \n3. **量子光学应用**：探索X射线-物质相互作用中的量子相干效应。  \n预期应用前景包括超快磁动力学研究、催化反应原位观测等。需进一步解决电子束热效应对相位稳定性的影响，以及更高重复频率下的系统稳定性问题。",
  "classification": {
    "category": "分类编号: 5\n分类名称: 加速器设计\n置信度: high",
    "confidence": 0.8
  },
  "keywords": [
    "free-electron laser",
    "self-seeded FEL",
    "fresh-bunch",
    "slotted foil",
    "corrugated wakefield structure",
    "phase-locked pulses",
    "hard X-ray",
    "femtosecond time scale"
  ],
  "summary": "该论文开发了一种基于自种子自由电子激光的可调谐、相位锁定硬X射线脉冲序列生成技术，首次在9.7 keV波段实现阿秒级相位精度的脉冲控制，为超快X射线光谱学和量子光学实验提供了突破性工具。其核心贡献在于通过电子束整形和相位锁定方法解决了FEL辐射场的时序精密调控难题，推动了硬X射线相干操控技术的发展。",
  "error": null
}