{
  "timestamp": "2026-03-31T03:51:11.828647",
  "paper_id": "2603.28276v1",
  "analysis": "### 1. 研究主题分析\n该论文的核心研究内容是提升低温量热器（cryogenic calorimeters）在稀有事件探测中的灵敏度，特别是针对NUCLEUS实验（旨在探测相干弹性中微子-原子核散射，CEνNS）的探测器优化。研究属于加速器物理与粒子物理实验的交叉领域，具体分支为**低能粒子探测技术与暗物质/中微子探测实验**。技术路线聚焦于采用声子媒介的低温量热器（通常由CaWO₄等晶体材料制成），并通过过渡边缘传感器（TES）读取信号。论文提出了两种互补方法：一是通过系统扫描探测器工作点（如偏置电压、温度），绘制信噪比图谱以确定最优操作配置；二是利用探测器的双通道读出信息，结合二维最优滤波分析，融合多通道数据以降低能量阈值。这两种方法共同目标是在保持低能量阈值的同时，最大化信号识别能力，为极低能稀有事件（如中微子-原子核相互作用）探测提供技术基础。\n\n### 2. 技术创新点\n论文的创新点主要体现在两方面：**一是系统化的探测器工作点优化方法**，通过宽范围扫描信噪比，定量确定最佳操作配置，避免了传统试错法的低效性；**二是二维最优滤波分析技术**，利用双读出通道的信息关联性，通过多维信号处理降低噪声，从而有效降低能量阈值。相比现有技术，这些方法在**信号提取效率**和**噪声抑制**上具有显著突破，尤其针对TES读出的低温量热器，其创新在于将操作优化与数据分析结合，形成闭环优化流程。技术难点在于如何在极低温（毫开尔文级）环境下稳定实现工作点扫描，并处理多通道信号间的非理想耦合（如串扰）。此外，二维滤波需克服通道间噪声相关性建模的复杂性，这对算法设计和校准精度提出了高要求。\n\n### 3. 应用价值评估\n该研究在加速器物理领域的应用价值突出体现在**低能粒子探测场景**，例如用于探测来自加速器中微子源（如核反应堆、质子加速器）的CEνNS信号，或暗物质直接探测实验（如超轻暗物质搜索）。在加速器设施中，这类高灵敏度探测器可部署于**束流线末端或屏蔽实验区**，用于监测极弱相互作用过程。对加速器性能的提升主要体现在**探测极限的拓展**：通过降低能量阈值（论文中基线分辨率达~3 eV），能够探测更微小的能量沉积，从而增强对稀有事件的捕获能力，助力新物理发现（如中微子反常磁矩、暗物质候选粒子）。此外，该技术也可用于加速器本底辐射的精密测量，优化屏蔽设计。\n\n### 4. 技术难点解析\n论文解决的关键技术难题包括：**1）低温探测器工作点不稳定性**：TES在超导转变边缘对温度、电流波动极度敏感，传统单一工作点易偏离最优灵敏度。解决方案是通过自动化扫描系统，在保持低温稳定性的同时，快速映射信噪比空间；**2）低能信号易被噪声淹没**：通过双通道读出与二维最优滤波，利用信号在空间/时间上的相关性区分噪声，将能量阈值推向电子伏特级。创新点在于将探测器硬件优化与高级信号处理结合，形成协同增强。尚未完全解决的挑战包括：**长期运行中的探测器性能漂移**、**多探测器阵列规模化应用时的数据处理复杂度**，以及**极端低温环境下电子学集成度的限制**。\n\n### 5. 研究意义评价\n在理论层面，该研究推动了**低能粒子探测物理**的发展，为检验超越标准模型物理（如中微子非标准相互作用）提供了更精密的实验工具。在工程实践上，其系统化优化方法为低温探测器设计提供了标准化流程，二维滤波技术也可扩展至其他多通道探测系统（如超导纳米线单光子探测器）。在国际研究前沿中，NUCLEUS实验是CEνNS探测的领先项目之一，本文的灵敏度提升技术使其在**亚千电子伏特能区**具备竞争优势，与COHERENT、CONUS等实验形成互补。整体上，该工作体现了探测器物理从“硬件驱动”向“软硬件协同优化”的演进趋势。\n\n### 6. 未来发展展望\n后续研究方向可能包括：**1）扩展至更大规模探测器阵列**，研究多通道间的串扰抑制与并行处理算法；**2）结合机器学习方法**（如神经网络滤波）进一步优化信号识别效率；**3）探索新型晶体材料或传感器设计**（如超导量子干涉器件），突破现有能量分辨率极限。应用前景不仅限于中微子物理，还可扩展到**天体物理观测**（如太阳中微子）、**量子传感**等领域。需进一步研究的问题包括：降低技术成本以实现大规模部署、提高探测器在辐照环境下的抗损伤能力，以及开发实时信号处理系统以适应高计数率场景。长期看，该技术有望成为下一代低能粒子探测实验的标准配置。",
  "classification": {
    "category": "分类编号: 9\n分类名称: 其他\n置信度: high",
    "confidence": 0.8
  },
  "keywords": [
    "cryogenic calorimeters",
    "transition-edge sensors",
    "signal-to-noise ratio",
    "optimum filter analysis",
    "energy threshold",
    "phonon-mediated detectors",
    "baseline resolution",
    "rare event searches"
  ],
  "summary": "该论文提出了通过系统化工作点扫描和二维最优滤波分析两种互补方法，显著提升了低温量热器的探测灵敏度，为NUCLEUS实验探测相干弹性中微子-原子核散射等稀有事件提供了关键技术支撑。",
  "error": null
}