{
  "timestamp": "2025-11-17T02:47:57.875075",
  "paper_id": "2511.09786v1",
  "analysis": "### 1. 研究主题分析\n该论文的核心研究内容是利用平均力动力学理论（mean force kinetic theory）评估双组分（离子-电子）等离子体的输运系数，包括电导率、热导率、电热系数、热电系数和剪切粘度。研究通过理论计算与分子动力学模拟的对比，验证了平均力动力学理论在强耦合等离子体条件下的有效性。该研究属于等离子体物理领域，具体涉及等离子体输运性质和流体动力学行为的理论建模，与加速器物理中的束流动力学、等离子体加速器及高能量密度物理密切相关。技术路线采用理论推导与数值模拟相结合的方法：首先基于平均力动力学理论建立输运系数的解析表达式，然后通过分子动力学模拟（假设粒子间为排斥库仑相互作用）进行验证。这种方法避免了传统动力学理论在强耦合条件下的失效问题，为研究稠密等离子体提供了新途径。\n\n### 2. 技术创新点\n论文的主要创新点在于将平均力动力学理论系统应用于等离子体输运系数的计算，并首次在高达库仑耦合强度Γ≈20的强耦合条件下验证了其准确性。相比传统动力学理论（如Boltzmann或Fokker-Planck方程）仅在弱耦合条件下适用（Γ≪1），该理论将适用范围扩展了两个数量级。技术难点在于强耦合等离子体中粒子关联效应显著，传统微扰理论失效。论文通过引入平均力的概念，有效处理了多体相互作用，避免了直接求解复杂N体问题的困难。创新的挑战还包括如何确保分子动力学模拟在排斥库仑势下的数值稳定性，以及理论模型与模拟结果的一致性验证。\n\n### 3. 应用价值评估\n在加速器物理领域，该研究对等离子体加速器、惯性约束聚变装置和高亮度束流源的设计有重要应用价值。例如，在激光等离子体加速器（LWFA）中，稠密等离子体的输运性质直接影响束流品质和能量转换效率；在重离子加速器中，束流与背景等离子体的相互作用也需要精确的输运系数。通过提供更准确的输运系数模型，该研究有助于优化加速器参数（如聚焦强度、能量沉积控制），减少束流散射和能量损失，从而提升加速器效率和稳定性。此外，对于未来高能量密度物理实验装置（如欧洲XFEL或LCLS-II），该理论可为等离子体透镜和靶设计提供理论支持。\n\n### 4. 技术难点解析\n论文成功解决了强耦合等离子体中输运系数计算的长期难题。传统理论在Γ>0.1时因忽略粒子关联而失效，而该研究通过平均力动力学理论，将有效相互作用势与平衡分布函数结合，间接包含了多体关联效应。创新解决方案包括：1）采用平均力替代裸库仑势，简化了粒子相互作用的描述；2）利用分子动力学模拟验证理论，确保模型在强耦合区域的可靠性。然而，尚未完全解决的技术挑战包括：1）理论在极高耦合强度（Γ>20）或非平衡态下的适用性；2）实际等离子体中吸引相互作用和量子效应的忽略；3）模型在三维非均匀系统或 relativistic 等离子体中的扩展问题。\n\n### 5. 研究意义评价\n该研究对加速器物理学科的理论意义在于突破了传统输运理论的局限，为稠密等离子体流体动力学提供了更普适的框架。它填补了弱耦合与强耦合等离子体理论之间的空白，推动了多体物理与等离子体物理的交叉发展。在工程实践上，该理论可直接用于加速器束流冷却、等离子体源优化和辐射模拟等场景，提高设计精度。在国际研究前沿中，该工作属于强耦合等离子体输运性质研究的热点方向，与美国NIF、德国GSI等机构的实验研究形成互补，为下一代高能量密度装置提供了理论工具。\n\n### 6. 未来发展展望\n后续研究可能围绕以下方向展开：1）将理论扩展至多组分等离子体或包含磁场的情况，以适用于聚变装置或磁约束加速器；2）结合第一性原理计算，研究量子效应对输运系数的影响；3）开发高效数值算法，实现非平衡态或瞬态过程的模拟。预期应用前景包括新型等离子体加速器的实时控制和束流品质优化，以及在实验室天体物理和惯性约束聚变中的广泛应用。需进一步研究的问题包括：1）理论在极端条件（如超相对论等离子体）下的验证；2）实际材料中边界效应和杂质的影响；3）与实验数据的直接对比，以完善模型参数。",
  "classification": {
    "category": "分类编号: 9\n分类名称: 其他\n置信度: medium",
    "confidence": 0.8
  },
  "keywords": [
    "Mean force kinetic theory",
    "Plasma hydrodynamics",
    "Electrical conductivity",
    "Thermal conductivity",
    "Shear viscosity",
    "Coulomb coupling strength",
    "Molecular dynamics simulations",
    "Two-component plasma"
  ],
  "summary": "该论文通过平均力动力学理论首次在强耦合等离子体（Γ≈20）中精确计算了多种输运系数，突破了传统理论在强耦合条件下的局限，为稠密等离子体加速器和聚变装置的设计提供了更可靠的理论工具。",
  "error": null
}