{
  "arxiv_id": "2606.19766v1",
  "url": "https://arxiv.org/abs/2606.19766v1",
  "pdf_url": "https://arxiv.org/pdf/2606.19766v1.pdf",
  "title": "Operational characterization of LAPPD Generation 2: charge sharing, delayed pulses, and dark-count behavior",
  "abstract": "We present a study of charge sharing and electronic cross-talk in second-generation Large-Area Picosecond Photodetectors (LAPPD Gen 2). The LAPPD is a vacuum-based device consisting of a photocathode, two microchannel plates, and a resistive anode that capacitively couples to an 8 $\\times$ 8 pixelated readout board (25.4 mm $\\times$ 25.4 mm pixel area). Using a picosecond pulsed laser, we measure signal distributions across the resistive anode and quantify coupling between target and neighboring pixels. We further examine the relationship between dark-count rate and LAPPD voltage settings, identifying decay behavior characterized by fast, intermediate, and slow relaxation timescales. We additionally observe the LAPPD behaving as a resonant cavity by injecting electrical pulses into the readout board. To further interpret observed signals, we develop a pulse-classification method and identify additional features at approximately 60 ns and 110 ns. Finally, we implement a first-principles Monte Carlo simulation to model the radial and temporal distributions of observed signals, including contributions from electron backscatter and potential ion afterpulsing. The simulation shows reasonable agreement with the experimentally derived pulse classifications.",
  "authors": [
    "S. -W. Stradleigh",
    "J. A. Foot",
    "R. Zhang",
    "V. A. Li"
  ],
  "published": "2026-06-18T04:06:13Z",
  "updated": "2026-06-18T04:06:13Z",
  "categories": [
    "physics.ins-det",
    "hep-ex"
  ],
  "primary_category": "physics.ins-det"
}