{
  "timestamp": "2025-08-16T02:44:59.891001",
  "paper_id": "2507.07109v2",
  "analysis": "### 1. 研究主题分析  \n该论文的核心研究内容是利用深度神经网络（DNN）优化VAMOS++磁谱仪对原子电荷态（atomic charge state）和原子序数（atomic number）的分析效率。VAMOS++是一种多参数磁谱仪，通过离子光学磁元件和多探测器堆栈实现粒子轨迹、速度、质量电荷比等参数的测量。传统方法依赖人工分析电离室数据，耗时数月且易受探测器非均匀性等因素干扰。本研究提出了一种基于部分标记事件（fractionally labelled events）训练的DNN方法，仅需少量高分辨率标记数据即可自动分类大部分事件，显著提升分析速度。该研究属于加速器物理中的核反应产物诊断技术分支，技术路线结合了机器学习与核探测技术，实现了数据分析的智能化和自动化。\n\n---\n\n### 2. 技术创新点  \n论文的主要创新点在于将深度学习引入核物理实验数据分析，具体包括：  \n1. **部分标记训练**：仅需对最低且分辨率最佳的原子电荷态或原子序数事件进行精确标记，即可训练DNN模型推广至其他事件，解决了传统方法需全样本标记的瓶颈。  \n2. **抗干扰能力**：通过DNN自动学习探测器非均匀性（如电离室入口窗厚度变化）的隐含特征，减少人工修正偏差。  \n3. **效率突破**：将分析时间从数月缩短至数小时，且结果标准化、可重复。技术难点在于如何确保DNN在少量标记数据下的泛化能力，以及如何处理探测器噪声与非线性响应。作者通过数据增强和网络结构优化（如卷积神经网络特征提取）应对这些挑战。\n\n---\n\n### 3. 应用价值评估  \n该研究在加速器物理领域具有显著应用价值：  \n1. **设施适配性**：适用于任何需要高精度电荷态和原子序数分析的磁谱仪系统，如重离子加速器（GANIL、FAIR等）的核反应实验。  \n2. **性能提升**：通过快速、自动化分析，可实时优化束流参数或实验设计，提高数据产出效率。例如，在放射性束实验中，快速识别产物电荷态有助于调整分离器设置。  \n3. **标准化输出**：消除人工分析的主观性，提升实验结果的可比性，尤其适合多实验室协作项目。  \n\n---\n\n### 4. 技术难点解析  \n论文解决的关键技术难题包括：  \n1. **探测器非理想性**：电离室入口窗厚度不均导致能量测量偏差，传统方法需复杂校正。DNN通过端到端学习直接建模噪声分布，绕过物理建模的复杂性。  \n2. **小样本学习**：仅依赖部分标记数据训练时，DNN易过拟合。作者可能采用了迁移学习或半监督学习（如自训练算法）提升泛化性。  \n未完全解决的问题可能包括极端稀疏标记场景下的模型稳定性，以及如何将方法推广至更高原子序数（Z>50）的低统计区域。  \n\n---\n\n### 5. 研究意义评价  \n该研究的理论意义在于：  \n1. **学科交叉示范**：为加速器物理与人工智能的融合提供了成功案例，推动数据驱动型核物理研究的发展。  \n2. **方法学突破**：部分标记策略可扩展至其他探测器系统（如硅微条探测器），具有普适性。  \n在国际前沿中，该研究属于“智能核仪器”（Smart Nuclear Instrumentation）的热点方向，与欧洲核子中心（CERN）的AI4EIC计划等技术趋势一致，体现了加速器诊断技术的智能化升级。  \n\n---\n\n### 6. 未来发展展望  \n后续研究方向可能包括：  \n1. **模型优化**：引入图神经网络（GNN）处理探测器间的拓扑关联，或利用物理约束损失函数提升DNN的物理合理性。  \n2. **实时应用**：部署轻量化模型至边缘计算设备，实现实验中的在线分析。  \n3. **扩展应用**：将该方法适配至其他谱仪（如SPEG、PRISMA），或用于更复杂的多参数关联分析（如角动量分布）。需进一步研究的问题包括模型在极低统计量下的鲁棒性，以及如何整合先验物理知识以提升解释性。  \n\n（注：以上分析基于摘要内容，若需更深入评估需结合全文数据与实验细节。）",
  "classification": {
    "category": "分类编号: 4\n分类名称: 束流诊断\n置信度: high",
    "confidence": 0.8
  },
  "keywords": [
    "VAMOS++ magnetic spectrometer",
    "deep neural networks",
    "atomic charge state",
    "atomic number",
    "magnetic rigidity",
    "ionization chamber",
    "trajectory reconstruction",
    "mass-over-charge ratio"
  ],
  "summary": "该论文提出了一种基于深度神经网络和部分标记事件训练的新方法，显著提升了VAMOS++磁谱仪对原子电荷态和原子序数的分析效率，将传统耗时数月的人工分析缩短至数小时，同时解决了探测器非均匀性干扰问题，为加速器物理实验提供了智能化、标准化的数据分析解决方案。这一研究推动了人工智能与核物理的交叉应用，为大型核设施的高效数据诊断树立了新范式。",
  "error": null
}