{
  "timestamp": "2025-10-08T02:35:41.595332",
  "paper_id": "2510.04743v1",
  "analysis": "### 1. 研究主题分析\n本论文的核心研究内容是开发一种基于YAG:Ce闪烁体的低能单电子探测器，重点在于实现亚微米级别的空间分辨率（1微米）和高探测效率（17 keV时效率与纯度均超过0.8，30 keV时达到0.96）。该研究属于加速器物理中的电子光学与探测器技术分支，具体涉及电子束探测与成像系统的优化。研究的技术路线采用闪烁体材料（YAG:Ce）结合光学成像系统，通过电子与闪烁体相互作用产生光子，再经高灵敏度相机捕获信号，从而实现单电子事件的定位与计数。这种方法结合了材料科学与光学探测技术，旨在解决低能电子探测中的分辨率与效率瓶颈。\n\n### 2. 技术创新点\n论文的主要技术创新点包括：首先，实现了在低能电子（17 keV）下的亚微米级空间分辨率（1微米），这显著优于传统闪烁体探测器的性能；其次，通过优化YAG:Ce闪烁体的响应特性，在低能条件下仍能保持高探测效率与纯度（17 keV时>0.8，30 keV时>0.96），解决了低能电子探测中信号弱、噪声干扰大的问题。相比现有技术，该探测器在分辨率和低能适应性方面具有突破，传统探测器如微通道板（MCP）或直接成像探测器在低能下分辨率受限或效率较低。技术难点在于如何平衡闪烁体的发光效率与空间分辨率，同时抑制噪声，作者通过材料优化和光学系统设计克服了这些挑战。\n\n### 3. 应用价值评估\n这项研究在加速器物理领域具有显著的实际应用价值，尤其适用于电子显微镜、电子衍射实验和先进电子光学系统。例如，在透射电子显微镜（TEM）或扫描电子显微镜（SEM）中，该探测器可提升低能电子成像的精度，适用于材料科学、生物学等领域的微观结构分析。此外，论文提到该探测器支持大气压下的电子衍射研究，这意味着它可能应用于环境电子显微镜或原位实验，减少对高真空环境的依赖。对加速器性能的提升主要体现在提高探测灵敏度和分辨率，从而扩展了低能电子实验的应用范围，例如在量子光学或表面科学中实现更精确的电子束操控。\n\n### 4. 技术难点解析\n论文解决的关键技术难题包括：低能电子探测中的信号弱化和空间分辨率限制。传统探测器在低能下易受噪声影响，且分辨率往往达不到亚微米级别。作者采用YAG:Ce闪烁体作为核心材料，利用其高发光效率和稳定性，结合精密光学系统（如高灵敏度相机）来放大和捕获信号，从而在低能条件下实现高分辨率探测。创新的解决方案还包括优化电子-光子转换过程，以减少信号损失。然而，尚未完全解决的技术挑战包括：在更低能量（如<10 keV）下的性能维持、大规模集成到现有加速器系统中的兼容性，以及长期稳定性问题（如闪烁体老化）。\n\n### 5. 研究意义评价\n从理论意义看，该研究推动了电子探测器物理的发展，为低能电子相互作用机制提供了新见解，尤其是在闪烁体材料与电子能量关系方面。对工程实践而言，它提供了可复制的探测器设计框架，指导实际应用中如何平衡分辨率、效率和成本，对加速器与显微镜的升级具有直接参考价值。在国际研究前沿中，该论文处于电子探测器技术的前沿，与当前追求高分辨率、低能应用的趋势一致，例如在量子计算和纳米科学中，类似技术正被广泛探索。总体而言，它填补了低能电子探测的空白，具有较高的学术和工程影响力。\n\n### 6. 未来发展展望\n可能的后续研究方向包括：进一步优化探测器在更低电子能量（如5-10 keV）下的性能，探索新型闪烁体材料（如钙钛矿或有机材料）以提升效率，以及集成到多模态探测系统中实现多功能应用。预期的应用前景广阔，可扩展到生物成像、环境科学和工业检测领域，例如在大气压电子衍射中实现实时样品分析。需要进一步研究的问题包括：如何提高探测器的长期稳定性和抗辐射能力，以及降低成本以实现商业化；此外，与人工智能结合进行信号处理可能成为未来热点，以应对大数据量下的实时分析挑战。",
  "classification": {
    "category": "分类编号: 4\n分类名称: 束流诊断\n置信度: high",
    "confidence": 0.8
  },
  "keywords": [
    "YAG:Ce scintillator",
    "single-electron detector",
    "spatial resolution",
    "electron energy",
    "electron diffraction",
    "detection efficiency",
    "electron optics",
    "mean free path"
  ],
  "summary": "该论文开发了一种基于YAG:Ce闪烁体的低能单电子探测器，实现了在17-30 keV能量范围内亚微米级空间分辨率（1微米）和高探测效率（最高达0.96）的突破。这项技术填补了低能电子探测领域的性能空白，为电子显微镜和电子衍射等应用提供了更高精度的探测解决方案。",
  "error": null
}