{
  "arxiv_id": "2605.31327v1",
  "url": "https://arxiv.org/abs/2605.31327v1",
  "pdf_url": "https://arxiv.org/pdf/2605.31327v1.pdf",
  "title": "Optimization of the light detection system of the ICARUS detector",
  "abstract": "The ICARUS detector, a key component of the Short Baseline Neutrino (SBN) Program at Fermi National Acelerator Laboratory (FNAL), is a 600-ton Liquid Argon Time Projection Chamber (LArTPC) equipped with a Light Detection System (LDS) that uses 360 Hamamatsu R5912-MOD 8-inch photomultiplier tubes (PMTs), specifically designed to operate under cryogenic conditions ($\\sim 87 \\ K$). These PMTs feed the trigger signal to the readout, improve the spatial and timing resolution of the events, and contribute to cosmic rays mitigation. During operation at FNAL, a progressive degradation in the PMT gain was observed. We developed an experimental setup to investigate the temperature dependence of PMT performance. Gain measurements were carried out from room temperature to $-70 ^\\circ C$ using an environmental chamber. The results show that, while the PMTs exhibit stable performance at room temperature, a significant and irreversible reduction in gain emerges at lower temperatures. Al though $-70 ^\\circ C$ remains above the liquid argon temperatures, the trend clearly reveals a gain-sensitive degradation mechanism. A simplified physical model was developed to reproduce and interpret the observed behavior. Based on these findings, a series of mitigation strategies were implemented in the ICARUS detector to preserve PMT performance and ensure reliable operation under cryogenic conditions.",
  "authors": [
    "C. Saia",
    "C. Petta",
    "G. L. Raselli",
    "M. Rossella"
  ],
  "published": "2026-05-29T14:01:31Z",
  "updated": "2026-05-29T14:01:31Z",
  "categories": [
    "physics.ins-det"
  ],
  "primary_category": "physics.ins-det"
}